{
  "project_info": {
    "project_number": "195415299290",
    "project_id": "sales-app-3fd1b",
    "storage_bucket": "sales-app-3fd1b.appspot.com"
  },
  "client": [
    {
      "client_info": {
        "mobilesdk_app_id": "1:195415299290:android:60cbb8e74de219572401e3",
        "android_client_info": {
          "package_name": "com.bytes18.example.salesview"
        }
      },
      "oauth_client": [
        {
          "client_id": "195415299290-ga4g5921nlfcv8am0kiv06usmrapkgch.apps.googleusercontent.com",
          "client_type": 3
        }
      ],
      "api_key": [
        {
          "current_key": "AIzaSyDJAfn3q0sNhfEAZc1g4cGKTPruixZQ6wc"
        }
      ],
      "services": {
        "appinvite_service": {
          "other_platform_oauth_client": [
            {
              "client_id": "195415299290-ga4g5921nlfcv8am0kiv06usmrapkgch.apps.googleusercontent.com",
              "client_type": 3
            }
          ]
        }
      }
    }
  ],
  "configuration_version": "1"
}